bulma/__init__.py
bulma/templates/bulma/checkbox.html
bulma/templates/bulma/field.html
bulma/templates/bulma/file.html
bulma/templates/bulma/form.html
bulma/templates/bulma/formset.html
bulma/templates/bulma/input.html
bulma/templates/bulma/other.html
bulma/templates/bulma/radio.html
bulma/templates/bulma/select.html
bulma/templates/bulma/textarea.html
bulma/templatetags/bulma.py
django_bulma_forms-0.1.6.dist-info/LICENSE
django_bulma_forms-0.1.6.dist-info/METADATA
django_bulma_forms-0.1.6.dist-info/WHEEL
django_bulma_forms-0.1.6.dist-info/top_level.txt
django_bulma_forms-0.1.6.dist-info/RECORD
