Metadata-Version: 2.2
Name: django-bulma-forms
Version: 0.1.6
Author-email: Tom Hubrecht <pypi@mail.hubrecht.ovh>
License: LICENCE PUBLIQUE DE L'UNION EUROPÉENNE v. 1.2
Project-URL: Homepage, https://git.hubrecht.ovh/hubrecht/django-bulma-forms
Project-URL: Issues, https://git.hubrecht.ovh/hubrecht/django-bulma-forms/issues
Keywords: django,bulma
Classifier: Development Status :: 4 - Beta
Classifier: Intended Audience :: Developers
Classifier: License :: OSI Approved :: European Union Public Licence 1.2 (EUPL 1.2)
Classifier: Programming Language :: Python :: 3
License-File: LICENSE
Requires-Dist: django
